{"v":"5.12.1","fr":60,"ip":0,"op":129,"w":430,"h":430,"nm":"wired-gradient-1165-dog-training","ddd":0,"assets":[{"id":"comp_0","nm":"hover-pinch","fr":60,"layers":[{"ddd":0,"ind":1,"ty":0,"nm":"mask","td":1,"refId":"comp_1","sr":1,"ks":{"o":{"a":0,"k":100,"ix":11},"r":{"a":0,"k":0,"ix":10},"p":{"a":0,"k":[215,215,0],"ix":2,"l":2},"a":{"a":0,"k":[215,215,0],"ix":1,"l":2},"s":{"a":0,"k":[100,100,100],"ix":6,"l":2}},"ao":0,"w":430,"h":430,"ip":0,"op":844,"st":0,"bm":0},{"ddd":0,"ind":2,"ty":4,"nm":"gradient","tt":1,"tp":1,"sr":1,"ks":{"o":{"a":0,"k":100,"ix":11},"r":{"a":1,"k":[{"i":{"x":[0.4],"y":[1]},"o":{"x":[0.333],"y":[0]},"t":0,"s":[-94]},{"t":129,"s":[266]}],"ix":10},"p":{"a":0,"k":[271.941,190.46,0],"ix":2,"l":2},"a":{"a":0,"k":[0,0,0],"ix":1,"l":2},"s":{"a":0,"k":[240,240,100],"ix":6,"l":2}},"ao":0,"ef":[{"ty":29,"nm":"Gaussian Blur","np":5,"mn":"ADBE Gaussian Blur 2","ix":1,"en":1,"ef":[{"ty":0,"nm":"Blurriness","mn":"ADBE Gaussian Blur 2-0001","ix":1,"v":{"a":0,"k":175,"ix":1}},{"ty":7,"nm":"Blur Dimensions","mn":"ADBE Gaussian Blur 2-0002","ix":2,"v":{"a":0,"k":1,"ix":2}},{"ty":7,"nm":"Repeat Edge Pixels","mn":"ADBE Gaussian Blur 2-0003","ix":3,"v":{"a":0,"k":1,"ix":3}}]}],"shapes":[{"ty":"gr","it":[{"ind":0,"ty":"sh","ix":1,"ks":{"a":0,"k":{"i":[[-97.478,0],[0,-97.478],[97.478,0],[30.894,26.574],[0,53.531]],"o":[[97.478,0],[0,97.478],[-43.948,0],[-37.631,-32.369],[0,-97.478]],"v":[[0,-176.5],[176.5,0],[0,176.5],[-105.29,115.869],[-176.5,0]],"c":true},"ix":2},"nm":"Path 1","mn":"ADBE Vector Shape - Group","hd":false},{"ty":"fl","c":{"a":0,"k":[0,0.078,0.761,1],"ix":4,"x":"var $bm_rt;\n$bm_rt = comp('wired-gradient-1165-dog-training').layer('control').effect('secondary')('Color');"},"o":{"a":0,"k":100,"ix":5},"r":1,"bm":0,"nm":".secondary","mn":"ADBE Vector Graphic - Fill","hd":false,"cl":"secondary"},{"ty":"tr","p":{"a":0,"k":[113.242,-118.884],"ix":2},"a":{"a":0,"k":[0,0],"ix":1},"s":{"a":0,"k":[100,100],"ix":3},"r":{"a":0,"k":0,"ix":6},"o":{"a":0,"k":100,"ix":7},"sk":{"a":0,"k":0,"ix":4},"sa":{"a":0,"k":0,"ix":5},"nm":"Transform"}],"nm":"primary.design","np":2,"cix":2,"bm":0,"ix":1,"mn":"ADBE Vector Group","hd":false,"cl":"design"},{"ty":"gr","it":[{"d":1,"ty":"el","s":{"a":0,"k":[500,500],"ix":2},"p":{"a":0,"k":[0,0],"ix":3},"nm":"Ellipse Path 1","mn":"ADBE Vector Shape - Ellipse","hd":false},{"ty":"fl","c":{"a":0,"k":[0,0.878,0.725,1],"ix":4,"x":"var $bm_rt;\n$bm_rt = comp('wired-gradient-1165-dog-training').layer('control').effect('primary')('Color');"},"o":{"a":0,"k":100,"ix":5},"r":1,"bm":0,"nm":".primary","mn":"ADBE Vector Graphic - Fill","hd":false,"cl":"primary"},{"ty":"tr","p":{"a":0,"k":[0,0],"ix":2},"a":{"a":0,"k":[0,0],"ix":1},"s":{"a":0,"k":[100,100],"ix":3},"r":{"a":0,"k":0,"ix":6},"o":{"a":0,"k":100,"ix":7},"sk":{"a":0,"k":0,"ix":4},"sa":{"a":0,"k":0,"ix":5},"nm":"Transform"}],"nm":"secondary.design","np":2,"cix":2,"bm":0,"ix":2,"mn":"ADBE Vector Group","hd":false,"cl":"design"}],"ip":0,"op":300,"st":0,"ct":1,"bm":0}]},{"id":"comp_1","nm":"mask","fr":60,"layers":[{"ddd":0,"ind":1,"ty":4,"nm":"Hand","sr":1,"ks":{"o":{"a":0,"k":100,"ix":11},"r":{"a":1,"k":[{"i":{"x":[0.667],"y":[1]},"o":{"x":[0.333],"y":[0]},"t":0,"s":[0]},{"i":{"x":[0.667],"y":[1]},"o":{"x":[0.333],"y":[0]},"t":22,"s":[-19]},{"i":{"x":[0.667],"y":[1]},"o":{"x":[0.333],"y":[0]},"t":63,"s":[0]},{"i":{"x":[0.667],"y":[1]},"o":{"x":[0.333],"y":[0]},"t":79,"s":[-19]},{"t":120,"s":[0]}],"ix":10},"p":{"a":1,"k":[{"i":{"x":0.667,"y":1},"o":{"x":0.333,"y":0},"t":0,"s":[48.008,174.834,0],"to":[-1,-1.333,0],"ti":[0,0,0]},{"i":{"x":0.667,"y":1},"o":{"x":0.333,"y":0},"t":16,"s":[42.008,166.834,0],"to":[0,0,0],"ti":[0,0,0]},{"i":{"x":0.667,"y":1},"o":{"x":0.333,"y":0},"t":57,"s":[48.008,174.834,0],"to":[0,0,0],"ti":[0,0,0]},{"i":{"x":0.667,"y":1},"o":{"x":0.333,"y":0},"t":73,"s":[42.008,166.834,0],"to":[0,0,0],"ti":[-1,-1.333,0]},{"t":114,"s":[48.008,174.834,0]}],"ix":2,"l":2},"a":{"a":0,"k":[-70,-5,0],"ix":1,"l":2},"s":{"a":0,"k":[100,100,100],"ix":6,"l":2}},"ao":0,"shapes":[{"ty":"gr","it":[{"ind":0,"ty":"sh","ix":1,"ks":{"a":1,"k":[{"i":{"x":0.667,"y":1},"o":{"x":0.333,"y":0},"t":0,"s":[{"i":[[0,0],[0,0],[0.001,2.366],[2.044,3.395],[5.421,0.298],[0,0],[4.878,1.231],[24.589,-8.334],[0,0],[-15.664,-3.198],[0,0],[-9.943,5.586],[0,0],[0,0],[0,0],[6.572,-3.521],[0,0],[0,0]],"o":[[0,0],[2.366,0],[-0.002,-3.793],[-1.815,-3.014],[0,0],[-5.031,0],[-16.336,-4.122],[0,0],[0,0],[0,0],[11.174,2.281],[0,0],[0,0],[0,0],[-3.522,-6.568],[0,0],[0,0],[0,0]],"v":[[-12.102,-4.709],[26.965,-4.709],[31.26,-9.012],[28.231,-21.821],[17.508,-28.85],[-15.364,-28.85],[-30.289,-30.68],[-90.325,-22.476],[-90.325,21.1],[-37.777,25.909],[-11.08,31.359],[21.66,26.236],[64.58,1.991],[90.325,-12.552],[86.165,-22.227],[67.892,-27.75],[46.873,-16.491],[31.153,-8.07]],"c":false}]},{"i":{"x":0.667,"y":1},"o":{"x":0.333,"y":0},"t":28,"s":[{"i":[[0,0],[0,0],[0.404,2.331],[2.592,2.997],[5.393,-0.629],[0,0],[4.878,1.231],[24.589,-8.334],[0,0],[-15.664,-3.198],[0,0],[-10.644,10.406],[0,0],[0,0],[0,0],[1.351,-7.332],[0,0],[0,0]],"o":[[0,0],[2.332,-0.403],[-0.648,-3.737],[-2.301,-2.661],[0,0],[-5.031,0],[-16.336,-4.122],[0,0],[0,0],[0,0],[11.174,2.281],[0,0],[0,0],[0,0],[-7.33,-1.348],[0,0],[0,0],[0,0]],"v":[[-18.427,-4.771],[22.042,-9.945],[25.542,-14.917],[20.377,-27.023],[8.613,-32.124],[-15.038,-29.795],[-30.289,-30.68],[-90.325,-22.476],[-90.325,21.1],[-37.777,25.909],[-11.08,31.359],[29.872,17.14],[57.235,-19.483],[62.556,-57.278],[52.4,-60.066],[36.68,-49.237],[33.044,-26.974],[25.596,-13.971]],"c":false}]},{"i":{"x":0.667,"y":1},"o":{"x":0.333,"y":0},"t":69,"s":[{"i":[[0,0],[0,0],[0.001,2.366],[2.044,3.395],[5.421,0.298],[0,0],[4.878,1.231],[24.589,-8.334],[0,0],[-15.664,-3.198],[0,0],[-9.943,5.586],[0,0],[0,0],[0,0],[6.572,-3.521],[0,0],[0,0]],"o":[[0,0],[2.366,0],[-0.002,-3.793],[-1.815,-3.014],[0,0],[-5.031,0],[-16.336,-4.122],[0,0],[0,0],[0,0],[11.174,2.281],[0,0],[0,0],[0,0],[-3.522,-6.568],[0,0],[0,0],[0,0]],"v":[[-12.102,-4.709],[26.965,-4.709],[31.26,-9.012],[28.231,-21.821],[17.508,-28.85],[-15.364,-28.85],[-30.289,-30.68],[-90.325,-22.476],[-90.325,21.1],[-37.777,25.909],[-11.08,31.359],[21.66,26.236],[64.58,1.991],[90.325,-12.552],[86.165,-22.227],[67.892,-27.75],[46.873,-16.491],[31.153,-8.07]],"c":false}]},{"i":{"x":0.667,"y":1},"o":{"x":0.333,"y":0},"t":85,"s":[{"i":[[0,0],[0,0],[0.404,2.331],[2.592,2.997],[5.393,-0.629],[0,0],[4.878,1.231],[24.589,-8.334],[0,0],[-15.664,-3.198],[0,0],[-10.644,10.406],[0,0],[0,0],[0,0],[1.351,-7.332],[0,0],[0,0]],"o":[[0,0],[2.332,-0.403],[-0.648,-3.737],[-2.301,-2.661],[0,0],[-5.031,0],[-16.336,-4.122],[0,0],[0,0],[0,0],[11.174,2.281],[0,0],[0,0],[0,0],[-7.33,-1.348],[0,0],[0,0],[0,0]],"v":[[-18.427,-4.771],[22.042,-9.945],[25.542,-14.917],[20.377,-27.023],[8.613,-32.124],[-15.038,-29.795],[-30.289,-30.68],[-90.325,-22.476],[-90.325,21.1],[-37.777,25.909],[-11.08,31.359],[29.872,17.14],[57.235,-19.483],[62.556,-57.278],[52.4,-60.066],[36.68,-49.237],[33.044,-26.974],[25.596,-13.971]],"c":false}]},{"t":126,"s":[{"i":[[0,0],[0,0],[0.001,2.366],[2.044,3.395],[5.421,0.298],[0,0],[4.878,1.231],[24.589,-8.334],[0,0],[-15.664,-3.198],[0,0],[-9.943,5.586],[0,0],[0,0],[0,0],[6.572,-3.521],[0,0],[0,0]],"o":[[0,0],[2.366,0],[-0.002,-3.793],[-1.815,-3.014],[0,0],[-5.031,0],[-16.336,-4.122],[0,0],[0,0],[0,0],[11.174,2.281],[0,0],[0,0],[0,0],[-3.522,-6.568],[0,0],[0,0],[0,0]],"v":[[-12.102,-4.709],[26.965,-4.709],[31.26,-9.012],[28.231,-21.821],[17.508,-28.85],[-15.364,-28.85],[-30.289,-30.68],[-90.325,-22.476],[-90.325,21.1],[-37.777,25.909],[-11.08,31.359],[21.66,26.236],[64.58,1.991],[90.325,-12.552],[86.165,-22.227],[67.892,-27.75],[46.873,-16.491],[31.153,-8.07]],"c":false}]}],"ix":2},"nm":"Path 1","mn":"ADBE Vector Shape - Group","hd":false},{"ty":"st","c":{"a":0,"k":[0.070588238537,0.074509806931,0.192156866193,1],"ix":3},"o":{"a":0,"k":100,"ix":4},"w":{"a":0,"k":12,"ix":5,"x":"var $bm_rt;\n$bm_rt = $bm_mul($bm_div(value, 2), comp('wired-gradient-1165-dog-training').layer('control').effect('stroke')('Menu'));"},"lc":2,"lj":2,"bm":0,"nm":".primary","mn":"ADBE Vector Graphic - Stroke","hd":false,"cl":"primary"},{"ty":"tr","p":{"a":0,"k":[0,0],"ix":2},"a":{"a":0,"k":[0,0],"ix":1},"s":{"a":0,"k":[100,100],"ix":3},"r":{"a":0,"k":0,"ix":6},"o":{"a":0,"k":100,"ix":7},"sk":{"a":0,"k":0,"ix":4},"sa":{"a":0,"k":0,"ix":5},"nm":"Transform"}],"nm":"Group 1","np":2,"cix":2,"bm":0,"ix":1,"mn":"ADBE Vector Group","hd":false}],"ip":0,"op":844,"st":0,"ct":1,"bm":0},{"ddd":0,"ind":2,"ty":4,"nm":"Dog","sr":1,"ks":{"o":{"a":0,"k":100,"ix":11},"r":{"a":0,"k":0,"ix":10},"p":{"a":0,"k":[292.552,227.936,0],"ix":2,"l":2},"a":{"a":0,"k":[327.552,262.936,0],"ix":1,"l":2},"s":{"a":0,"k":[100,100,100],"ix":6,"l":2}},"ao":0,"shapes":[{"ty":"gr","it":[{"ind":0,"ty":"sh","ix":1,"ks":{"a":1,"k":[{"i":{"x":0.332,"y":1},"o":{"x":0.167,"y":0.167},"t":0,"s":[{"i":[[0,0],[-0.356,15.962],[0,0],[0,0],[-1.105,-0.768],[0,0],[0,0],[0,0],[-9.976,-7.157]],"o":[[8.281,-13.826],[0,0],[-66.846,-16.14],[0,0],[21.152,-26.744],[7.85,-10.314],[0,0],[1.133,12.225],[0,0]],"v":[[-36.623,81.351],[-22.373,36.399],[-20.33,10.151],[-62.69,-41.436],[-24.096,-42.607],[24.933,-42.878],[56.099,-81.351],[49.57,-7.001],[67.068,23.5]],"c":false}]},{"i":{"x":0.667,"y":1},"o":{"x":0.333,"y":0},"t":41,"s":[{"i":[[0,0],[1.195,15.908],[0,0],[0,0],[-1.313,-0.293],[0,0],[0,0],[0,0],[-10.615,-6.149]],"o":[[3.309,-15.748],[0,0],[-67.932,10.299],[0,0],[9.473,-32.725],[3.369,-12.504],[0,0],[5.663,10.881],[0,0]],"v":[[-33.462,91.286],[-29.678,46.642],[-29.576,28.09],[-88.235,-3.645],[-52.973,-19.295],[-7.718,-38.053],[6.593,-85.407],[28.616,-14.161],[58.012,25.135]],"c":false}]},{"i":{"x":0.833,"y":0.833},"o":{"x":0.167,"y":0},"t":66,"s":[{"i":[[0,0],[-3.843,15.497],[0,0],[0,0],[-0.91,-0.992],[0,0],[0,0],[0,0],[-9.976,-7.157]],"o":[[11.108,-11.678],[0,0],[-61.69,-30.386],[0,0],[26.495,-21.463],[9.918,-8.344],[0,0],[-1.571,12.176],[0,0]],"v":[[-47.611,61.976],[-23.863,21.235],[-16.123,-3.928],[-46.158,-63.539],[-8.244,-56.23],[39.655,-45.759],[78.488,-76.473],[55.837,-5.358],[67.068,23.5]],"c":false}]},{"i":{"x":0.667,"y":1},"o":{"x":0.167,"y":0.167},"t":75,"s":[{"i":[[0,0],[-2.232,15.712],[0,0],[0,0],[-1.044,-0.816],[0,0],[0,0],[0,0],[-9.976,-7.157]],"o":[[9.085,-13.048],[0,0],[-64.796,-19.569],[0,0],[22.27,-25.109],[8.286,-9.7],[0,0],[0.436,12.076],[0,0]],"v":[[-37.462,61.927],[-23.174,28.24],[-19.173,6.478],[-57.939,-46.566],[-19.947,-45.576],[28.25,-43.124],[61.01,-79.202],[50.47,-6.5],[67.068,23.5]],"c":false}]},{"i":{"x":0.667,"y":1},"o":{"x":0.167,"y":0},"t":88,"s":[{"i":[[0,0],[-0.356,15.962],[0,0],[0,0],[-1.199,-0.612],[0,0],[0,0],[0,0],[-9.976,-7.157]],"o":[[6.73,-14.644],[0,0],[-68.413,-6.969],[0,0],[17.348,-29.355],[6.386,-11.279],[0,0],[2.773,11.96],[0,0]],"v":[[-36.465,81.355],[-22.373,36.399],[-22.726,18.6],[-71.662,-26.797],[-33.579,-33.167],[14.965,-40.054],[40.652,-82.381],[44.219,-7.831],[67.068,23.5]],"c":false}]},{"t":120,"s":[{"i":[[0,0],[-0.356,15.962],[0,0],[0,0],[-1.105,-0.768],[0,0],[0,0],[0,0],[-9.976,-7.157]],"o":[[8.281,-13.826],[0,0],[-66.846,-16.14],[0,0],[21.152,-26.744],[7.85,-10.314],[0,0],[1.133,12.225],[0,0]],"v":[[-36.623,81.351],[-22.373,36.399],[-20.33,10.151],[-62.69,-41.436],[-24.096,-42.607],[24.933,-42.878],[56.099,-81.351],[49.57,-7.001],[67.068,23.5]],"c":false}]}],"ix":2},"nm":"Path 1","mn":"ADBE Vector Shape - Group","hd":false},{"ty":"st","c":{"a":0,"k":[0.070588238537,0.074509806931,0.192156866193,1],"ix":3},"o":{"a":0,"k":100,"ix":4},"w":{"a":0,"k":12,"ix":5,"x":"var $bm_rt;\n$bm_rt = $bm_mul($bm_div(value, 2), comp('wired-gradient-1165-dog-training').layer('control').effect('stroke')('Menu'));"},"lc":2,"lj":2,"bm":0,"nm":".primary","mn":"ADBE Vector Graphic - Stroke","hd":false,"cl":"primary"},{"ty":"tr","p":{"a":0,"k":[368.505,197.103],"ix":2},"a":{"a":0,"k":[0,0],"ix":1},"s":{"a":0,"k":[100,100],"ix":3},"r":{"a":0,"k":0,"ix":6},"o":{"a":0,"k":100,"ix":7},"sk":{"a":0,"k":0,"ix":4},"sa":{"a":0,"k":0,"ix":5},"nm":"Transform"}],"nm":"Group 1","np":2,"cix":2,"bm":0,"ix":1,"mn":"ADBE Vector Group","hd":false},{"ty":"gr","it":[{"ind":0,"ty":"sh","ix":1,"ks":{"a":1,"k":[{"i":{"x":0.833,"y":0.833},"o":{"x":0.167,"y":0.167},"t":0,"s":[{"i":[[0,0],[17.037,3.059],[0,0],[0,0],[-20.745,-3.789],[0,0],[-11.678,-20.19]],"o":[[0,0],[-20.413,-3.665],[0,0],[0,0],[30.88,5.64],[0,0],[0,0]],"v":[[17.056,-55.748],[-34.055,-64.924],[-95.294,-75.918],[-88.414,-35.633],[-26.179,-24.266],[66.461,-7.347],[95.294,75.918]],"c":false}]},{"i":{"x":0.833,"y":0.833},"o":{"x":0.167,"y":0.167},"t":12,"s":[{"i":[[0,0],[17.307,0.455],[0,0],[0,0],[-20.124,-1.893],[0,0],[-11.678,-20.19]],"o":[[0,0],[-21.328,-0.935],[0,0],[0,0],[30.919,2.72],[0,0],[0,0]],"v":[[18.638,-50.331],[-33.61,-55.028],[-92.796,-56.368],[-81.571,-17.768],[-22.964,-15.366],[66.568,-4.517],[95.294,75.918]],"c":false}]},{"i":{"x":0.833,"y":0.833},"o":{"x":0.167,"y":0.167},"t":41,"s":[{"i":[[0,0],[17.959,-5.837],[0,0],[0,0],[-18.624,2.69],[0,0],[-11.678,-20.19]],"o":[[0,0],[-23.541,5.663],[0,0],[0,0],[31.013,-4.336],[0,0],[0,0]],"v":[[19.898,-45.781],[-32.535,-31.115],[-86.759,-9.122],[-65.033,25.405],[-15.194,6.144],[66.828,2.32],[95.294,75.918]],"c":false}]},{"i":{"x":0.833,"y":0.833},"o":{"x":0.167,"y":0.167},"t":44,"s":[{"i":[[0,0],[17.443,-3.904],[0,0],[0,0],[-18.595,2.777],[0,0],[-11.678,-20.19]],"o":[[0,0],[-22.57,4.23],[0,0],[0,0],[31.014,-4.47],[0,0],[0,0]],"v":[[19.458,-47.257],[-32.514,-30.662],[-86.644,-8.229],[-64.72,26.222],[-15.047,6.551],[66.833,2.449],[95.294,75.918]],"c":false}]},{"i":{"x":0.332,"y":1},"o":{"x":0.167,"y":0.167},"t":47,"s":[{"i":[[0,0],[17.164,-2.857],[0,0],[0,0],[-18.58,2.824],[0,0],[-11.678,-20.19]],"o":[[0,0],[-22.045,3.453],[0,0],[0,0],[31.015,-4.542],[0,0],[0,0]],"v":[[18.128,-49.949],[-32.503,-30.417],[-86.583,-7.744],[-64.551,26.664],[-14.967,6.771],[66.835,2.519],[95.294,75.918]],"c":false}]},{"i":{"x":0.833,"y":0.833},"o":{"x":0.333,"y":0},"t":50,"s":[{"i":[[0,0],[17.092,-2.59],[0,0],[0,0],[-18.576,2.836],[0,0],[-11.678,-20.19]],"o":[[0,0],[-21.91,3.255],[0,0],[0,0],[31.016,-4.56],[0,0],[0,0]],"v":[[16.218,-54.562],[-32.5,-30.355],[-86.567,-7.621],[-64.507,26.777],[-14.947,6.828],[66.836,2.537],[95.294,75.918]],"c":false}]},{"i":{"x":0.833,"y":0.833},"o":{"x":0.167,"y":0.167},"t":53,"s":[{"i":[[0,0],[17.03,-2.079],[0,0],[0,0],[-18.622,2.229],[0,0],[-11.678,-20.19]],"o":[[0,0],[-21.757,2.635],[0,0],[0,0],[30.899,-3.638],[0,0],[0,0]],"v":[[13.789,-59.591],[-33.01,-33.913],[-87.256,-13.748],[-66.521,21.002],[-16.485,3.5],[66.815,1.995],[95.294,75.918]],"c":false}]},{"i":{"x":0.833,"y":0.833},"o":{"x":0.167,"y":0.167},"t":60,"s":[{"i":[[0,0],[16.692,0.686],[0,0],[0,0],[-18.87,-1.063],[0,0],[-11.678,-20.19]],"o":[[0,0],[-20.927,-0.723],[0,0],[0,0],[30.269,1.362],[0,0],[0,0]],"v":[[8.645,-70.799],[-35.771,-53.204],[-90.992,-46.969],[-77.439,-10.312],[-24.825,-14.539],[66.704,-0.942],[95.294,75.918]],"c":false}]},{"i":{"x":0.833,"y":0.833},"o":{"x":0.167,"y":0.167},"t":63,"s":[{"i":[[0,0],[16.504,2.216],[0,0],[0,0],[-18.629,-3.615],[0,0],[-11.678,-20.19]],"o":[[0,0],[-20.467,-2.582],[0,0],[0,0],[29.613,5.376],[0,0],[0,0]],"v":[[6.634,-74.114],[-37.3,-63.884],[-93.06,-65.359],[-83.484,-27.648],[-29.442,-24.525],[66.642,-2.568],[95.294,75.918]],"c":false}]},{"i":{"x":0.667,"y":1},"o":{"x":0.167,"y":0.167},"t":67,"s":[{"i":[[0,0],[16.267,4.155],[0,0],[0,0],[-18.324,-6.847],[0,0],[-11.678,-20.19]],"o":[[0,0],[-19.884,-4.937],[0,0],[0,0],[28.782,10.459],[0,0],[0,0]],"v":[[6.454,-75.261],[-39.236,-77.408],[-95.679,-88.649],[-91.138,-49.601],[-35.289,-37.172],[66.564,-4.627],[95.294,75.918]],"c":false}]},{"i":{"x":0.833,"y":0.833},"o":{"x":0.167,"y":0},"t":75,"s":[{"i":[[0,0],[15.954,6.715],[0,0],[0,0],[-17.921,-11.115],[0,0],[-11.678,-20.19]],"o":[[0,0],[-19.115,-8.046],[0,0],[0,0],[27.685,17.171],[0,0],[0,0]],"v":[[15.569,-75.623],[-41.793,-95.268],[-99.138,-119.405],[-101.246,-78.591],[-43.011,-53.873],[66.461,-7.347],[95.294,75.918]],"c":false}]},{"i":{"x":0.833,"y":0.833},"o":{"x":0.167,"y":0.167},"t":79,"s":[{"i":[[0,0],[16.177,5.779],[0,0],[0,0],[-18.448,-9.488],[0,0],[-11.678,-20.19]],"o":[[0,0],[-19.382,-6.924],[0,0],[0,0],[28.299,14.643],[0,0],[0,0]],"v":[[16.798,-66.813],[-40.572,-89.176],[-98.718,-109.948],[-98.569,-69.391],[-39.509,-48.091],[66.461,-7.347],[95.294,75.918]],"c":false}]},{"i":{"x":0.667,"y":1},"o":{"x":0.167,"y":0.167},"t":86,"s":[{"i":[[0,0],[16.719,3.499],[0,0],[0,0],[-19.733,-5.526],[0,0],[-11.678,-20.19]],"o":[[0,0],[-20.032,-4.192],[0,0],[0,0],[29.795,8.487],[0,0],[0,0]],"v":[[16.938,-56.54],[-37.6,-74.338],[-97.696,-86.914],[-92.049,-46.983],[-30.981,-34.011],[66.461,-7.347],[95.294,75.918]],"c":false}]},{"i":{"x":0.667,"y":1},"o":{"x":0.167,"y":0},"t":97,"s":[{"i":[[0,0],[17.268,1.19],[0,0],[0,0],[-21.034,-1.513],[0,0],[-11.678,-20.19]],"o":[[0,0],[-20.69,-1.425],[0,0],[0,0],[31.31,2.252],[0,0],[0,0]],"v":[[17.215,-55.744],[-34.591,-59.313],[-96.661,-63.589],[-85.446,-24.29],[-22.344,-19.752],[66.461,-7.347],[95.294,75.918]],"c":false}]},{"t":129,"s":[{"i":[[0,0],[17.037,3.059],[0,0],[0,0],[-20.745,-3.789],[0,0],[-11.678,-20.19]],"o":[[0,0],[-20.413,-3.665],[0,0],[0,0],[30.88,5.64],[0,0],[0,0]],"v":[[17.056,-55.748],[-34.055,-64.924],[-95.294,-75.918],[-88.414,-35.633],[-26.179,-24.266],[66.461,-7.347],[95.294,75.918]],"c":false}]}],"ix":2},"nm":"Path 1","mn":"ADBE Vector Shape - Group","hd":false},{"ty":"st","c":{"a":0,"k":[0.070588238537,0.074509806931,0.192156866193,1],"ix":3},"o":{"a":0,"k":100,"ix":4},"w":{"a":0,"k":12,"ix":5,"x":"var $bm_rt;\n$bm_rt = $bm_mul($bm_div(value, 2), comp('wired-gradient-1165-dog-training').layer('control').effect('stroke')('Menu'));"},"lc":2,"lj":2,"bm":0,"nm":".primary","mn":"ADBE Vector Graphic - Stroke","hd":false,"cl":"primary"},{"ty":"tr","p":{"a":0,"k":[314.825,334.202],"ix":2},"a":{"a":0,"k":[0,0],"ix":1},"s":{"a":0,"k":[100,100],"ix":3},"r":{"a":0,"k":0,"ix":6},"o":{"a":0,"k":100,"ix":7},"sk":{"a":0,"k":0,"ix":4},"sa":{"a":0,"k":0,"ix":5},"nm":"Transform"}],"nm":"Group 3","np":2,"cix":2,"bm":0,"ix":2,"mn":"ADBE Vector Group","hd":false},{"ty":"gr","it":[{"ind":0,"ty":"sh","ix":1,"ks":{"a":1,"k":[{"i":{"x":0.332,"y":1},"o":{"x":0.167,"y":0.167},"t":0,"s":[{"i":[[0,0],[22.248,7.313]],"o":[[-23.438,19.868],[0,0]],"v":[[39.839,-10.429],[-39.839,7.263]],"c":false}]},{"i":{"x":0.667,"y":1},"o":{"x":0.333,"y":0},"t":41,"s":[{"i":[[0,0],[22.833,5.113]],"o":[[-21.379,22.032],[0,0]],"v":[[29.945,-7.837],[-47.572,17.489]],"c":false}]},{"i":{"x":0.667,"y":1},"o":{"x":0.167,"y":0},"t":66,"s":[{"i":[[0,0],[20.107,12.007]],"o":[[-23.438,19.868],[0,0]],"v":[[39.839,-10.429],[-40.382,-7.699]],"c":false}]},{"i":{"x":0.667,"y":1},"o":{"x":0.167,"y":0},"t":88,"s":[{"i":[[0,0],[22.248,7.313]],"o":[[-20.542,22.85],[0,0]],"v":[[37.293,-12.557],[-39.839,7.263]],"c":false}]},{"t":120,"s":[{"i":[[0,0],[22.248,7.313]],"o":[[-23.438,19.868],[0,0]],"v":[[39.839,-10.429],[-39.839,7.263]],"c":false}]}],"ix":2},"nm":"Path 1","mn":"ADBE Vector Shape - Group","hd":false},{"ty":"st","c":{"a":0,"k":[0.031372550875,0.658823549747,0.541176497936,1],"ix":3},"o":{"a":0,"k":100,"ix":4},"w":{"a":0,"k":12,"ix":5,"x":"var $bm_rt;\n$bm_rt = $bm_mul($bm_div(value, 2), comp('wired-gradient-1165-dog-training').layer('control').effect('stroke')('Menu'));"},"lc":2,"lj":2,"bm":0,"nm":".secondary","mn":"ADBE Vector Graphic - Stroke","hd":false,"cl":"secondary"},{"ty":"tr","p":{"a":0,"k":[386.406,221.864],"ix":2},"a":{"a":0,"k":[0,0],"ix":1},"s":{"a":0,"k":[100,100],"ix":3},"r":{"a":0,"k":0,"ix":6},"o":{"a":0,"k":100,"ix":7},"sk":{"a":0,"k":0,"ix":4},"sa":{"a":0,"k":0,"ix":5},"nm":"Transform"}],"nm":"Group 4","np":2,"cix":2,"bm":0,"ix":3,"mn":"ADBE Vector Group","hd":false}],"ip":0,"op":844,"st":0,"ct":1,"bm":0}]}],"layers":[{"ddd":0,"ind":1,"ty":3,"nm":"control","sr":1,"ks":{"o":{"a":0,"k":0,"ix":11},"r":{"a":0,"k":0,"ix":10},"p":{"a":0,"k":[0,0],"ix":2,"l":2},"a":{"a":0,"k":[0,0,0],"ix":1,"l":2},"s":{"a":0,"k":[100,100,100],"ix":6,"l":2}},"ao":0,"ef":[{"ty":5,"nm":"stroke","np":3,"mn":"Pseudo/@@xnf7OPSyTpiGVhduC8yMzw","ix":1,"en":1,"ef":[{"ty":7,"nm":"Menu","mn":"Pseudo/@@xnf7OPSyTpiGVhduC8yMzw-0001","ix":1,"v":{"a":0,"k":2,"ix":1}}]},{"ty":5,"nm":"primary","np":3,"mn":"ADBE Color Control","ix":2,"en":1,"ef":[{"ty":2,"nm":"Color","mn":"ADBE Color Control-0001","ix":1,"v":{"a":0,"k":[0,0.878,0.725],"ix":1}}]},{"ty":5,"nm":"secondary","np":3,"mn":"ADBE Color Control","ix":3,"en":1,"ef":[{"ty":2,"nm":"Color","mn":"ADBE Color Control-0001","ix":1,"v":{"a":0,"k":[0,0.078,0.761],"ix":1}}]}],"ip":0,"op":130,"st":0,"bm":0},{"ddd":0,"ind":2,"ty":0,"nm":"hover-pinch","refId":"comp_0","sr":1,"ks":{"o":{"a":0,"k":100,"ix":11},"r":{"a":0,"k":0,"ix":10},"p":{"a":0,"k":[215,215,0],"ix":2,"l":2},"a":{"a":0,"k":[215,215,0],"ix":1,"l":2},"s":{"a":0,"k":[100,100,100],"ix":6,"l":2}},"ao":0,"w":430,"h":430,"ip":0,"op":139,"st":0,"bm":0}],"markers":[{"tm":0,"cm":"default:hover-pinch","dr":129}],"props":{}}